LICENSE
MANIFEST.in
setup.py
HackerNews.egg-info/PKG-INFO
HackerNews.egg-info/SOURCES.txt
HackerNews.egg-info/dependency_links.txt
HackerNews.egg-info/requires.txt
HackerNews.egg-info/top_level.txt
hn/__init__.py
hn/constants.py
hn/hn.py
hn/utils.py
tests/__init__.py
tests/test_leaders.py
tests/test_pagination.py
tests/test_stories_dict_structure.py
tests/test_story_class.py
tests/test_story_fromid.py
tests/test_story_get_comments.py
tests/test_utils.py